collie_watch/__init__.py
collie_watch/collie_cli.py
collie_watch/exports.py
collie_watch/main_module.py
collie_watch/utils.py
collie_watch/widgets/__init__.py
collie_watch/widgets/alignment.py
collie_watch/widgets/button.py
collie_watch/widgets/center.py
collie_watch/widgets/column.py
collie_watch/widgets/container.py
collie_watch/widgets/dropdown.py
collie_watch/widgets/file_input.py
collie_watch/widgets/file_list.py
collie_watch/widgets/horizontal_filled_pill.py
collie_watch/widgets/icon.py
collie_watch/widgets/icons_list.py
collie_watch/widgets/image.py
collie_watch/widgets/loader.py
collie_watch/widgets/menu_region.py
collie_watch/widgets/radio_button_group.py
collie_watch/widgets/raw_html.py
collie_watch/widgets/row.py
collie_watch/widgets/scroll_view.py
collie_watch/widgets/sized_box.py
collie_watch/widgets/text.py
collie_watch/widgets/text_field.py
collie_watch/widgets/tooltip.py
collie_watch/widgets/widget.py
collie_watch-0.0.58.dist-info/entry_points.txt
collie_watch-0.0.58.dist-info/WHEEL
collie_watch-0.0.58.dist-info/METADATA
collie_watch-0.0.58.dist-info/RECORD
