Metadata-Version: 2.1
Name: collie_watch
Version: 0.0.58
Summary: A python package to interact with and receive info from running scripts
Author-email: Knz13 <otaviomaya@gmail.com>
Requires-Python: >=3.7
Classifier: Programming Language :: Python :: 3
Classifier: License :: OSI Approved :: MIT License
Classifier: Operating System :: OS Independent
Requires-Dist: supabase==1.0.3
Requires-Dist: websocket-client==1.6.2
Requires-Dist: beautifulsoup4==4.12.2
Requires-Dist: python-dotenv==1.0.0
Requires-Dist: Pillow==10.1.0
Requires-Dist: numpy==1.26.2
Requires-Dist: psutil==5.9.6
Project-URL: Bug Tracker, https://github.com/knz13/collie_watch/issues
Project-URL: Homepage, https://github.com/knz13/collie_watch
